NCryptoServer/LICENSE
NCryptoServer/__init__.py
NCryptoServer/client_manager.py
NCryptoServer/launcher.py
NCryptoServer/main_window.py
NCryptoServer/server_instance_holder.py
NCryptoServer/Database/ServerDB.db
NCryptoServer/Database/Table-fill.md
NCryptoServer/Database/__init__.py
NCryptoServer/Database/db_model.py
NCryptoServer/Database/server_storage.py
NCryptoServer/Database/test_db_model.py
NCryptoServer/Database/test_server_storage.py
NCryptoServer/Database/Query/query-insert-chatroom.sql
NCryptoServer/Database/Query/query-insert-chatroom_client.sql
NCryptoServer/Database/Query/query-insert-client.sql
NCryptoServer/Database/Query/query-insert-client_contacts.sql
NCryptoServer/Log/__init__.py
NCryptoServer/Log/server_log_config.py
NCryptoServer/Transmitter/__init__.py
NCryptoServer/Transmitter/client_connection.py
NCryptoServer/Transmitter/server_connection_acceptor.py
NCryptoServer/Transmitter/server_receiver.py
NCryptoServer/Transmitter/server_sender.py
NCryptoServer/UI/__init__.py
NCryptoServer/UI/ui_main_window.py
NCryptoServer/Utils/__init__.py
NCryptoServer/Utils/constants.py
NCryptoServer-0.5.3.dist-info/METADATA
NCryptoServer-0.5.3.dist-info/RECORD
NCryptoServer-0.5.3.dist-info/WHEEL
NCryptoServer-0.5.3.dist-info/entry_points.txt
NCryptoServer-0.5.3.dist-info/top_level.txt
